BusMessageParser/ParserMain.py
BusMessageParser/__init__.py
BusMessageParser/CommonBasic/CommonFunc.py
BusMessageParser/CommonBasic/__init__.py
BusMessageParser/GetRtpcData/GetData.py
BusMessageParser/GetRtpcData/__init__.py
BusMessageParser/OtherBasicFunc/NotCanAscFileRead.py
BusMessageParser/OtherBasicFunc/__init__.py
busmessageparser-1.1.1.dist-info/licenses/LICENSE
busmessageparser-1.1.1.dist-info/METADATA
busmessageparser-1.1.1.dist-info/WHEEL
busmessageparser-1.1.1.dist-info/top_level.txt
busmessageparser-1.1.1.dist-info/RECORD
