Metadata-Version: 2.4
Name: BusMessageParser
Version: 1.1.1
Summary: 总线报文记录文件检测
Author: Abyss
Author-email: 
License-File: LICENSE
Dynamic: author
Dynamic: description
Dynamic: license-file
Dynamic: summary
